mx2/__init__.py
mx2-0.0.7.dist-info/LICENCE.txt
mx2-0.0.7.dist-info/METADATA
mx2-0.0.7.dist-info/WHEEL
mx2-0.0.7.dist-info/top_level.txt
mx2-0.0.7.dist-info/RECORD
